{
  "gitSyncId": "66030000b3a93a77ec50aa7f_660c1a34fa166e4e6e578205",
  "id": "procurementRequestListing_findRequestsByCreationDate",
  "pluginId": "bonita-api-plugin",
  "pluginType": "API",
  "unpublishedAction": {
    "actionConfiguration": {
      "autoGeneratedHeaders": [],
      "body": "",
      "bodyFormData": [],
      "encodeParamsToggle": true,
      "formData": {
        "apiContentType": "none"
      },
      "headers": [],
      "httpMethod": "GET",
      "httpVersion": "HTTP11",
      "paginationType": "PAGE_NO",
      "path": "/bdm/businessData/com.company.model.Request",
      "pluginSpecifiedTemplates": [
        {
          "value": true
        }
      ],
      "queryParameters": [
        {
          "key": "p",
          "value": "0"
        },
        {
          "key": "c",
          "value": "20"
        },
        {
          "key": "q",
          "value": "findByCreationDate"
        },
        {
          "key": "f",
          "value": "creationDate=01-01-2024"
        }
      ],
      "timeoutInMillisecond": 10000
    },
    "confirmBeforeExecute": false,
    "datasource": {
      "id": "bonita",
      "isAutoGenerated": false,
      "name": "bonita",
      "pluginId": "bonita-api-plugin"
    },
    "dynamicBindingPathList": [],
    "executeOnLoad": false,
    "name": "findRequestsByCreationDate",
    "pageId": "procurementRequestListing",
    "userSetOnLoad": false
  }
}